{
    "cloud": {
        "name": "cloud",
        "description": "Links to useful resources available on the cloud",
        "descriptionLocalizations": {
            "es-ES": "Enlaces a recursos útiles disponibles en la nube",
            "pt-BR": "Links para recursos úteis disponíveis na nuvem",
            "it-IT": "Collegamenti a risorse utili disponibili sul cloud"
        },
        "options": {
            "platform": {
                "name": "platform",
                "nameLocalizations": {
                    "es-ES": "plataforma",
                    "pt-BR": "plataforma",
                    "it-IT": "piattaforma"
                },
                "description": "Select a platform",
                "descriptionLocalizations": {
                    "es-ES": "Seleccione una plataforma",
                    "pt-BR": "selecione a plataforma",
                    "it-IT": "Seleziona una piattaforma"
                }
            }
        }
    },
    "faq": {
        "name": "faq",
        "description": "Frequently Asked Questions",
        "descriptionLocalizations": {
            "es-ES": "Preguntas frecuentes",
            "pt-BR": "Perguntas Frequentes",
            "it-IT": "Domande frequenti"
        },
        "options": {
            "topic": {
                "name": "topic",
                "nameLocalizations": {
                    "en-ES": "tema",
                    "pt-BR": "tema",
                    "it-IT": "argomento"
                },
                "description": "Select a topic",
                "descriptionLocalizations": {
                    "en-ES": "Seleccione un tema",
                    "pt-BR": "selecione o tópico",
                    "it-IT": "Seleziona un argomento"
                }
            },
            "language": {
                "name": "language",
                "nameLocalizations": {
                    "en-ES": "idioma",
                    "pt-BR": "idioma",
                    "it-IT": "lingua"
                },
                "description": "Response Language (optional)",
                "descriptionLocalizations": {
                    "en-ES": "Idioma de respuesta (opcional)",
                    "pt-BR": "Idioma da resposta (opcional)",
                    "it-IT": "Lingua di risposta (opzionale)"
                },
                "choices": [
                    {"name": "en", "value": "en"},
                    {"name": "es", "value": "es"},
                    {"name": "it", "value": "it"},
                    {"name": "pt", "value": "pt"}
                ]
            },
            "private": {
                "name": "private",
                "nameLocalizations": {
                    "en-ES": "privado",
                    "pt-BR": "privado",
                    "it-IT": "silenzioso"
                },
                "description": "Only you can see the response (optional)",
                "descriptionLocalizations": {
                    "en-ES": "Solo tú puedes ver la respuesta (opcional)",
                    "pt-BR": "Apenas você vê a resposta (opcional)",
                    "it-IT": "Solo tu puoi vedere la risposta (opzionale)"
                }
            }
        }
    }
}